{
  "type": "File",
  "start": 0,
  "end": 886,
  "loc": {
    "start": {
      "line": 1,
      "column": 0
    },
    "end": {
      "line": 33,
      "column": 2
    }
  },
  "program": {
    "type": "Program",
    "start": 0,
    "end": 886,
    "loc": {
      "start": {
        "line": 1,
        "column": 0
      },
      "end": {
        "line": 33,
        "column": 2
      }
    },
    "sourceType": "module",
    "body": [
      {
        "type": "ExportNamedDeclaration",
        "start": 372,
        "end": 555,
        "loc": {
          "start": {
            "line": 10,
            "column": 0
          },
          "end": {
            "line": 17,
            "column": 2
          }
        },
        "specifiers": [],
        "source": null,
        "declaration": {
          "type": "VariableDeclaration",
          "start": 379,
          "end": 555,
          "loc": {
            "start": {
              "line": 10,
              "column": 7
            },
            "end": {
              "line": 17,
              "column": 2
            }
          },
          "declarations": [
            {
              "type": "VariableDeclarator",
              "start": 385,
              "end": 555,
              "loc": {
                "start": {
                  "line": 10,
                  "column": 13
                },
                "end": {
                  "line": 17,
                  "column": 2
                }
              },
              "id": {
                "type": "Identifier",
                "start": 385,
                "end": 399,
                "loc": {
                  "start": {
                    "line": 10,
                    "column": 13
                  },
                  "end": {
                    "line": 10,
                    "column": 27
                  },
                  "identifierName": "submitRegister"
                },
                "name": "submitRegister",
                "leadingComments": null
              },
              "init": {
                "type": "ArrowFunctionExpression",
                "start": 402,
                "end": 555,
                "loc": {
                  "start": {
                    "line": 10,
                    "column": 30
                  },
                  "end": {
                    "line": 17,
                    "column": 2
                  }
                },
                "id": {
                  "type": "Identifier",
                  "start": 385,
                  "end": 399,
                  "loc": {
                    "start": {
                      "line": 10,
                      "column": 13
                    },
                    "end": {
                      "line": 10,
                      "column": 27
                    },
                    "identifierName": "submitRegister"
                  },
                  "name": "submitRegister",
                  "leadingComments": null
                },
                "generator": false,
                "expression": true,
                "async": false,
                "params": [
                  {
                    "type": "Identifier",
                    "start": 403,
                    "end": 411,
                    "loc": {
                      "start": {
                        "line": 10,
                        "column": 31
                      },
                      "end": {
                        "line": 10,
                        "column": 39
                      },
                      "identifierName": "username"
                    },
                    "name": "username"
                  },
                  {
                    "type": "Identifier",
                    "start": 413,
                    "end": 422,
                    "loc": {
                      "start": {
                        "line": 10,
                        "column": 41
                      },
                      "end": {
                        "line": 10,
                        "column": 50
                      },
                      "identifierName": "firstname"
                    },
                    "name": "firstname"
                  },
                  {
                    "type": "Identifier",
                    "start": 424,
                    "end": 432,
                    "loc": {
                      "start": {
                        "line": 10,
                        "column": 52
                      },
                      "end": {
                        "line": 10,
                        "column": 60
                      },
                      "identifierName": "lastname"
                    },
                    "name": "lastname"
                  },
                  {
                    "type": "Identifier",
                    "start": 434,
                    "end": 439,
                    "loc": {
                      "start": {
                        "line": 10,
                        "column": 62
                      },
                      "end": {
                        "line": 10,
                        "column": 67
                      },
                      "identifierName": "email"
                    },
                    "name": "email"
                  },
                  {
                    "type": "Identifier",
                    "start": 441,
                    "end": 449,
                    "loc": {
                      "start": {
                        "line": 10,
                        "column": 69
                      },
                      "end": {
                        "line": 10,
                        "column": 77
                      },
                      "identifierName": "password"
                    },
                    "name": "password"
                  }
                ],
                "body": {
                  "type": "ObjectExpression",
                  "start": 455,
                  "end": 554,
                  "loc": {
                    "start": {
                      "line": 10,
                      "column": 83
                    },
                    "end": {
                      "line": 17,
                      "column": 1
                    }
                  },
                  "properties": [
                    {
                      "type": "ObjectProperty",
                      "start": 461,
                      "end": 484,
                      "loc": {
                        "start": {
                          "line": 11,
                          "column": 4
                        },
                        "end": {
                          "line": 11,
                          "column": 27
                        }
                      },
                      "method": false,
                      "shorthand": false,
                      "computed": false,
                      "key": {
                        "type": "Identifier",
                        "start": 461,
                        "end": 465,
                        "loc": {
                          "start": {
                            "line": 11,
                            "column": 4
                          },
                          "end": {
                            "line": 11,
                            "column": 8
                          },
                          "identifierName": "type"
                        },
                        "name": "type"
                      },
                      "value": {
                        "type": "StringLiteral",
                        "start": 467,
                        "end": 484,
                        "loc": {
                          "start": {
                            "line": 11,
                            "column": 10
                          },
                          "end": {
                            "line": 11,
                            "column": 27
                          }
                        },
                        "extra": {
                          "rawValue": "SUBMIT_REGISTER",
                          "raw": "'SUBMIT_REGISTER'"
                        },
                        "value": "SUBMIT_REGISTER"
                      }
                    },
                    {
                      "type": "ObjectProperty",
                      "start": 490,
                      "end": 498,
                      "loc": {
                        "start": {
                          "line": 12,
                          "column": 4
                        },
                        "end": {
                          "line": 12,
                          "column": 12
                        }
                      },
                      "method": false,
                      "shorthand": true,
                      "computed": false,
                      "key": {
                        "type": "Identifier",
                        "start": 490,
                        "end": 498,
                        "loc": {
                          "start": {
                            "line": 12,
                            "column": 4
                          },
                          "end": {
                            "line": 12,
                            "column": 12
                          },
                          "identifierName": "username"
                        },
                        "name": "username"
                      },
                      "value": {
                        "type": "Identifier",
                        "start": 490,
                        "end": 498,
                        "loc": {
                          "start": {
                            "line": 12,
                            "column": 4
                          },
                          "end": {
                            "line": 12,
                            "column": 12
                          },
                          "identifierName": "username"
                        },
                        "name": "username"
                      },
                      "extra": {
                        "shorthand": true
                      }
                    },
                    {
                      "type": "ObjectProperty",
                      "start": 504,
                      "end": 513,
                      "loc": {
                        "start": {
                          "line": 13,
                          "column": 4
                        },
                        "end": {
                          "line": 13,
                          "column": 13
                        }
                      },
                      "method": false,
                      "shorthand": true,
                      "computed": false,
                      "key": {
                        "type": "Identifier",
                        "start": 504,
                        "end": 513,
                        "loc": {
                          "start": {
                            "line": 13,
                            "column": 4
                          },
                          "end": {
                            "line": 13,
                            "column": 13
                          },
                          "identifierName": "firstname"
                        },
                        "name": "firstname"
                      },
                      "value": {
                        "type": "Identifier",
                        "start": 504,
                        "end": 513,
                        "loc": {
                          "start": {
                            "line": 13,
                            "column": 4
                          },
                          "end": {
                            "line": 13,
                            "column": 13
                          },
                          "identifierName": "firstname"
                        },
                        "name": "firstname"
                      },
                      "extra": {
                        "shorthand": true
                      }
                    },
                    {
                      "type": "ObjectProperty",
                      "start": 519,
                      "end": 527,
                      "loc": {
                        "start": {
                          "line": 14,
                          "column": 4
                        },
                        "end": {
                          "line": 14,
                          "column": 12
                        }
                      },
                      "method": false,
                      "shorthand": true,
                      "computed": false,
                      "key": {
                        "type": "Identifier",
                        "start": 519,
                        "end": 527,
                        "loc": {
                          "start": {
                            "line": 14,
                            "column": 4
                          },
                          "end": {
                            "line": 14,
                            "column": 12
                          },
                          "identifierName": "lastname"
                        },
                        "name": "lastname"
                      },
                      "value": {
                        "type": "Identifier",
                        "start": 519,
                        "end": 527,
                        "loc": {
                          "start": {
                            "line": 14,
                            "column": 4
                          },
                          "end": {
                            "line": 14,
                            "column": 12
                          },
                          "identifierName": "lastname"
                        },
                        "name": "lastname"
                      },
                      "extra": {
                        "shorthand": true
                      }
                    },
                    {
                      "type": "ObjectProperty",
                      "start": 533,
                      "end": 538,
                      "loc": {
                        "start": {
                          "line": 15,
                          "column": 4
                        },
                        "end": {
                          "line": 15,
                          "column": 9
                        }
                      },
                      "method": false,
                      "shorthand": true,
                      "computed": false,
                      "key": {
                        "type": "Identifier",
                        "start": 533,
                        "end": 538,
                        "loc": {
                          "start": {
                            "line": 15,
                            "column": 4
                          },
                          "end": {
                            "line": 15,
                            "column": 9
                          },
                          "identifierName": "email"
                        },
                        "name": "email"
                      },
                      "value": {
                        "type": "Identifier",
                        "start": 533,
                        "end": 538,
                        "loc": {
                          "start": {
                            "line": 15,
                            "column": 4
                          },
                          "end": {
                            "line": 15,
                            "column": 9
                          },
                          "identifierName": "email"
                        },
                        "name": "email"
                      },
                      "extra": {
                        "shorthand": true
                      }
                    },
                    {
                      "type": "ObjectProperty",
                      "start": 544,
                      "end": 552,
                      "loc": {
                        "start": {
                          "line": 16,
                          "column": 4
                        },
                        "end": {
                          "line": 16,
                          "column": 12
                        }
                      },
                      "method": false,
                      "shorthand": true,
                      "computed": false,
                      "key": {
                        "type": "Identifier",
                        "start": 544,
                        "end": 552,
                        "loc": {
                          "start": {
                            "line": 16,
                            "column": 4
                          },
                          "end": {
                            "line": 16,
                            "column": 12
                          },
                          "identifierName": "password"
                        },
                        "name": "password"
                      },
                      "value": {
                        "type": "Identifier",
                        "start": 544,
                        "end": 552,
                        "loc": {
                          "start": {
                            "line": 16,
                            "column": 4
                          },
                          "end": {
                            "line": 16,
                            "column": 12
                          },
                          "identifierName": "password"
                        },
                        "name": "password"
                      },
                      "extra": {
                        "shorthand": true
                      }
                    }
                  ],
                  "extra": {
                    "parenthesized": true,
                    "parenStart": 454
                  }
                },
                "trailingComments": null
              },
              "leadingComments": null,
              "trailingComments": null
            }
          ],
          "kind": "const",
          "leadingComments": [
            {
              "type": "CommentBlock",
              "value": "*\n * \n * @param {string} username  username  of the new user  \n * @param {string} firstname first name of the new user\n * @param {string} lastname   lastname of the new user\n * @param {string} email    email of the new user\n * @param {string} password password of the new user\n * @return {action} SUBMIT_REGISTER action and the payload of the data with the new user\n ",
              "start": 0,
              "end": 371,
              "loc": {
                "start": {
                  "line": 1,
                  "column": 0
                },
                "end": {
                  "line": 9,
                  "column": 3
                }
              }
            }
          ],
          "trailingComments": [
            {
              "type": "CommentBlock",
              "value": "*\n * @return {action} REGISTER_SUCCESS action\n ",
              "start": 557,
              "end": 608,
              "loc": {
                "start": {
                  "line": 19,
                  "column": 0
                },
                "end": {
                  "line": 21,
                  "column": 3
                }
              }
            }
          ]
        },
        "leadingComments": [
          {
            "type": "CommentBlock",
            "value": "*\n * \n * @param {string} username  username  of the new user  \n * @param {string} firstname first name of the new user\n * @param {string} lastname   lastname of the new user\n * @param {string} email    email of the new user\n * @param {string} password password of the new user\n * @return {action} SUBMIT_REGISTER action and the payload of the data with the new user\n ",
            "start": 0,
            "end": 371,
            "loc": {
              "start": {
                "line": 1,
                "column": 0
              },
              "end": {
                "line": 9,
                "column": 3
              }
            }
          }
        ],
        "trailingComments": [
          {
            "type": "CommentBlock",
            "value": "*\n * @return {action} REGISTER_SUCCESS action\n ",
            "start": 557,
            "end": 608,
            "loc": {
              "start": {
                "line": 19,
                "column": 0
              },
              "end": {
                "line": 21,
                "column": 3
              }
            }
          }
        ]
      },
      {
        "type": "ExportNamedDeclaration",
        "start": 609,
        "end": 680,
        "loc": {
          "start": {
            "line": 22,
            "column": 0
          },
          "end": {
            "line": 24,
            "column": 2
          }
        },
        "specifiers": [],
        "source": null,
        "declaration": {
          "type": "VariableDeclaration",
          "start": 616,
          "end": 680,
          "loc": {
            "start": {
              "line": 22,
              "column": 7
            },
            "end": {
              "line": 24,
              "column": 2
            }
          },
          "declarations": [
            {
              "type": "VariableDeclarator",
              "start": 622,
              "end": 680,
              "loc": {
                "start": {
                  "line": 22,
                  "column": 13
                },
                "end": {
                  "line": 24,
                  "column": 2
                }
              },
              "id": {
                "type": "Identifier",
                "start": 622,
                "end": 637,
                "loc": {
                  "start": {
                    "line": 22,
                    "column": 13
                  },
                  "end": {
                    "line": 22,
                    "column": 28
                  },
                  "identifierName": "registerSuccess"
                },
                "name": "registerSuccess",
                "leadingComments": null
              },
              "init": {
                "type": "ArrowFunctionExpression",
                "start": 640,
                "end": 680,
                "loc": {
                  "start": {
                    "line": 22,
                    "column": 31
                  },
                  "end": {
                    "line": 24,
                    "column": 2
                  }
                },
                "id": {
                  "type": "Identifier",
                  "start": 622,
                  "end": 637,
                  "loc": {
                    "start": {
                      "line": 22,
                      "column": 13
                    },
                    "end": {
                      "line": 22,
                      "column": 28
                    },
                    "identifierName": "registerSuccess"
                  },
                  "name": "registerSuccess",
                  "leadingComments": null
                },
                "generator": false,
                "expression": true,
                "async": false,
                "params": [],
                "body": {
                  "type": "ObjectExpression",
                  "start": 647,
                  "end": 679,
                  "loc": {
                    "start": {
                      "line": 22,
                      "column": 38
                    },
                    "end": {
                      "line": 24,
                      "column": 1
                    }
                  },
                  "properties": [
                    {
                      "type": "ObjectProperty",
                      "start": 653,
                      "end": 677,
                      "loc": {
                        "start": {
                          "line": 23,
                          "column": 4
                        },
                        "end": {
                          "line": 23,
                          "column": 28
                        }
                      },
                      "method": false,
                      "shorthand": false,
                      "computed": false,
                      "key": {
                        "type": "Identifier",
                        "start": 653,
                        "end": 657,
                        "loc": {
                          "start": {
                            "line": 23,
                            "column": 4
                          },
                          "end": {
                            "line": 23,
                            "column": 8
                          },
                          "identifierName": "type"
                        },
                        "name": "type"
                      },
                      "value": {
                        "type": "StringLiteral",
                        "start": 659,
                        "end": 677,
                        "loc": {
                          "start": {
                            "line": 23,
                            "column": 10
                          },
                          "end": {
                            "line": 23,
                            "column": 28
                          }
                        },
                        "extra": {
                          "rawValue": "REGISTER_SUCCESS",
                          "raw": "'REGISTER_SUCCESS'"
                        },
                        "value": "REGISTER_SUCCESS"
                      }
                    }
                  ],
                  "extra": {
                    "parenthesized": true,
                    "parenStart": 646
                  }
                },
                "trailingComments": null
              },
              "leadingComments": null,
              "trailingComments": null
            }
          ],
          "kind": "const",
          "leadingComments": [
            {
              "type": "CommentBlock",
              "value": "*\n * @return {action} REGISTER_SUCCESS action\n ",
              "start": 557,
              "end": 608,
              "loc": {
                "start": {
                  "line": 19,
                  "column": 0
                },
                "end": {
                  "line": 21,
                  "column": 3
                }
              }
            }
          ],
          "trailingComments": [
            {
              "type": "CommentBlock",
              "value": "*\n * @param {*} error the error \n * @return {action} REGISTER_ERROR action and the payload with the error\n ",
              "start": 682,
              "end": 793,
              "loc": {
                "start": {
                  "line": 26,
                  "column": 0
                },
                "end": {
                  "line": 29,
                  "column": 3
                }
              }
            }
          ]
        },
        "leadingComments": [
          {
            "type": "CommentBlock",
            "value": "*\n * @return {action} REGISTER_SUCCESS action\n ",
            "start": 557,
            "end": 608,
            "loc": {
              "start": {
                "line": 19,
                "column": 0
              },
              "end": {
                "line": 21,
                "column": 3
              }
            }
          }
        ],
        "trailingComments": [
          {
            "type": "CommentBlock",
            "value": "*\n * @param {*} error the error \n * @return {action} REGISTER_ERROR action and the payload with the error\n ",
            "start": 682,
            "end": 793,
            "loc": {
              "start": {
                "line": 26,
                "column": 0
              },
              "end": {
                "line": 29,
                "column": 3
              }
            }
          }
        ]
      },
      {
        "type": "ExportNamedDeclaration",
        "start": 794,
        "end": 886,
        "loc": {
          "start": {
            "line": 30,
            "column": 0
          },
          "end": {
            "line": 33,
            "column": 2
          }
        },
        "specifiers": [],
        "source": null,
        "declaration": {
          "type": "VariableDeclaration",
          "start": 801,
          "end": 886,
          "loc": {
            "start": {
              "line": 30,
              "column": 7
            },
            "end": {
              "line": 33,
              "column": 2
            }
          },
          "declarations": [
            {
              "type": "VariableDeclarator",
              "start": 807,
              "end": 886,
              "loc": {
                "start": {
                  "line": 30,
                  "column": 13
                },
                "end": {
                  "line": 33,
                  "column": 2
                }
              },
              "id": {
                "type": "Identifier",
                "start": 807,
                "end": 820,
                "loc": {
                  "start": {
                    "line": 30,
                    "column": 13
                  },
                  "end": {
                    "line": 30,
                    "column": 26
                  },
                  "identifierName": "registerError"
                },
                "name": "registerError",
                "leadingComments": null
              },
              "init": {
                "type": "ArrowFunctionExpression",
                "start": 823,
                "end": 886,
                "loc": {
                  "start": {
                    "line": 30,
                    "column": 29
                  },
                  "end": {
                    "line": 33,
                    "column": 2
                  }
                },
                "id": {
                  "type": "Identifier",
                  "start": 807,
                  "end": 820,
                  "loc": {
                    "start": {
                      "line": 30,
                      "column": 13
                    },
                    "end": {
                      "line": 30,
                      "column": 26
                    },
                    "identifierName": "registerError"
                  },
                  "name": "registerError",
                  "leadingComments": null
                },
                "generator": false,
                "expression": true,
                "async": false,
                "params": [
                  {
                    "type": "Identifier",
                    "start": 824,
                    "end": 829,
                    "loc": {
                      "start": {
                        "line": 30,
                        "column": 30
                      },
                      "end": {
                        "line": 30,
                        "column": 35
                      },
                      "identifierName": "error"
                    },
                    "name": "error"
                  }
                ],
                "body": {
                  "type": "ObjectExpression",
                  "start": 835,
                  "end": 885,
                  "loc": {
                    "start": {
                      "line": 30,
                      "column": 41
                    },
                    "end": {
                      "line": 33,
                      "column": 1
                    }
                  },
                  "properties": [
                    {
                      "type": "ObjectProperty",
                      "start": 841,
                      "end": 863,
                      "loc": {
                        "start": {
                          "line": 31,
                          "column": 4
                        },
                        "end": {
                          "line": 31,
                          "column": 26
                        }
                      },
                      "method": false,
                      "shorthand": false,
                      "computed": false,
                      "key": {
                        "type": "Identifier",
                        "start": 841,
                        "end": 845,
                        "loc": {
                          "start": {
                            "line": 31,
                            "column": 4
                          },
                          "end": {
                            "line": 31,
                            "column": 8
                          },
                          "identifierName": "type"
                        },
                        "name": "type"
                      },
                      "value": {
                        "type": "StringLiteral",
                        "start": 847,
                        "end": 863,
                        "loc": {
                          "start": {
                            "line": 31,
                            "column": 10
                          },
                          "end": {
                            "line": 31,
                            "column": 26
                          }
                        },
                        "extra": {
                          "rawValue": "REGISTER_ERROR",
                          "raw": "'REGISTER_ERROR'"
                        },
                        "value": "REGISTER_ERROR"
                      }
                    },
                    {
                      "type": "ObjectProperty",
                      "start": 869,
                      "end": 883,
                      "loc": {
                        "start": {
                          "line": 32,
                          "column": 4
                        },
                        "end": {
                          "line": 32,
                          "column": 18
                        }
                      },
                      "method": false,
                      "shorthand": false,
                      "computed": false,
                      "key": {
                        "type": "Identifier",
                        "start": 869,
                        "end": 876,
                        "loc": {
                          "start": {
                            "line": 32,
                            "column": 4
                          },
                          "end": {
                            "line": 32,
                            "column": 11
                          },
                          "identifierName": "payload"
                        },
                        "name": "payload"
                      },
                      "value": {
                        "type": "Identifier",
                        "start": 878,
                        "end": 883,
                        "loc": {
                          "start": {
                            "line": 32,
                            "column": 13
                          },
                          "end": {
                            "line": 32,
                            "column": 18
                          },
                          "identifierName": "error"
                        },
                        "name": "error"
                      }
                    }
                  ],
                  "extra": {
                    "parenthesized": true,
                    "parenStart": 834
                  }
                }
              },
              "leadingComments": null
            }
          ],
          "kind": "const",
          "leadingComments": [
            {
              "type": "CommentBlock",
              "value": "*\n * @param {*} error the error \n * @return {action} REGISTER_ERROR action and the payload with the error\n ",
              "start": 682,
              "end": 793,
              "loc": {
                "start": {
                  "line": 26,
                  "column": 0
                },
                "end": {
                  "line": 29,
                  "column": 3
                }
              }
            }
          ],
          "trailingComments": []
        },
        "leadingComments": [
          {
            "type": "CommentBlock",
            "value": "*\n * @param {*} error the error \n * @return {action} REGISTER_ERROR action and the payload with the error\n ",
            "start": 682,
            "end": 793,
            "loc": {
              "start": {
                "line": 26,
                "column": 0
              },
              "end": {
                "line": 29,
                "column": 3
              }
            }
          }
        ]
      }
    ],
    "directives": []
  },
  "comments": [
    {
      "type": "CommentBlock",
      "value": "*\n * \n * @param {string} username  username  of the new user  \n * @param {string} firstname first name of the new user\n * @param {string} lastname   lastname of the new user\n * @param {string} email    email of the new user\n * @param {string} password password of the new user\n * @return {action} SUBMIT_REGISTER action and the payload of the data with the new user\n ",
      "start": 0,
      "end": 371,
      "loc": {
        "start": {
          "line": 1,
          "column": 0
        },
        "end": {
          "line": 9,
          "column": 3
        }
      }
    },
    {
      "type": "CommentBlock",
      "value": "*\n * @return {action} REGISTER_SUCCESS action\n ",
      "start": 557,
      "end": 608,
      "loc": {
        "start": {
          "line": 19,
          "column": 0
        },
        "end": {
          "line": 21,
          "column": 3
        }
      }
    },
    {
      "type": "CommentBlock",
      "value": "*\n * @param {*} error the error \n * @return {action} REGISTER_ERROR action and the payload with the error\n ",
      "start": 682,
      "end": 793,
      "loc": {
        "start": {
          "line": 26,
          "column": 0
        },
        "end": {
          "line": 29,
          "column": 3
        }
      }
    }
  ],
  "tokens": [
    {
      "type": "CommentBlock",
      "value": "*\n * \n * @param {string} username  username  of the new user  \n * @param {string} firstname first name of the new user\n * @param {string} lastname   lastname of the new user\n * @param {string} email    email of the new user\n * @param {string} password password of the new user\n * @return {action} SUBMIT_REGISTER action and the payload of the data with the new user\n ",
      "start": 0,
      "end": 371,
      "loc": {
        "start": {
          "line": 1,
          "column": 0
        },
        "end": {
          "line": 9,
          "column": 3
        }
      }
    },
    {
      "type": {
        "label": "export",
        "keyword": "export",
        "beforeExpr": false,
        "startsExpr": false,
        "rightAssociative": false,
        "isLoop": false,
        "isAssign": false,
        "prefix": false,
        "postfix": false,
        "binop": null,
        "updateContext": null
      },
      "value": "export",
      "start": 372,
      "end": 378,
      "loc": {
        "start": {
          "line": 10,
          "column": 0
        },
        "end": {
          "line": 10,
          "column": 6
        }
      }
    },
    {
      "type": {
        "label": "const",
        "keyword": "const",
        "beforeExpr": false,
        "startsExpr": false,
        "rightAssociative": false,
        "isLoop": false,
        "isAssign": false,
        "prefix": false,
        "postfix": false,
        "binop": null,
        "updateContext": null
      },
      "value": "const",
      "start": 379,
      "end": 384,
      "loc": {
        "start": {
          "line": 10,
          "column": 7
        },
        "end": {
          "line": 10,
          "column": 12
        }
      }
    },
    {
      "type": {
        "label": "name",
        "beforeExpr": false,
        "startsExpr": true,
        "rightAssociative": false,
        "isLoop": false,
        "isAssign": false,
        "prefix": false,
        "postfix": false,
        "binop": null
      },
      "value": "submitRegister",
      "start": 385,
      "end": 399,
      "loc": {
        "start": {
          "line": 10,
          "column": 13
        },
        "end": {
          "line": 10,
          "column": 27
        }
      }
    },
    {
      "type": {
        "label": "=",
        "beforeExpr": true,
        "startsExpr": false,
        "rightAssociative": false,
        "isLoop": false,
        "isAssign": true,
        "prefix": false,
        "postfix": false,
        "binop": null,
        "updateContext": null
      },
      "value": "=",
      "start": 400,
      "end": 401,
      "loc": {
        "start": {
          "line": 10,
          "column": 28
        },
        "end": {
          "line": 10,
          "column": 29
        }
      }
    },
    {
      "type": {
        "label": "(",
        "beforeExpr": true,
        "startsExpr": true,
        "rightAssociative": false,
        "isLoop": false,
        "isAssign": false,
        "prefix": false,
        "postfix": false,
        "binop": null
      },
      "start": 402,
      "end": 403,
      "loc": {
        "start": {
          "line": 10,
          "column": 30
        },
        "end": {
          "line": 10,
          "column": 31
        }
      }
    },
    {
      "type": {
        "label": "name",
        "beforeExpr": false,
        "startsExpr": true,
        "rightAssociative": false,
        "isLoop": false,
        "isAssign": false,
        "prefix": false,
        "postfix": false,
        "binop": null
      },
      "value": "username",
      "start": 403,
      "end": 411,
      "loc": {
        "start": {
          "line": 10,
          "column": 31
        },
        "end": {
          "line": 10,
          "column": 39
        }
      }
    },
    {
      "type": {
        "label": ",",
        "beforeExpr": true,
        "startsExpr": false,
        "rightAssociative": false,
        "isLoop": false,
        "isAssign": false,
        "prefix": false,
        "postfix": false,
        "binop": null,
        "updateContext": null
      },
      "start": 411,
      "end": 412,
      "loc": {
        "start": {
          "line": 10,
          "column": 39
        },
        "end": {
          "line": 10,
          "column": 40
        }
      }
    },
    {
      "type": {
        "label": "name",
        "beforeExpr": false,
        "startsExpr": true,
        "rightAssociative": false,
        "isLoop": false,
        "isAssign": false,
        "prefix": false,
        "postfix": false,
        "binop": null
      },
      "value": "firstname",
      "start": 413,
      "end": 422,
      "loc": {
        "start": {
          "line": 10,
          "column": 41
        },
        "end": {
          "line": 10,
          "column": 50
        }
      }
    },
    {
      "type": {
        "label": ",",
        "beforeExpr": true,
        "startsExpr": false,
        "rightAssociative": false,
        "isLoop": false,
        "isAssign": false,
        "prefix": false,
        "postfix": false,
        "binop": null,
        "updateContext": null
      },
      "start": 422,
      "end": 423,
      "loc": {
        "start": {
          "line": 10,
          "column": 50
        },
        "end": {
          "line": 10,
          "column": 51
        }
      }
    },
    {
      "type": {
        "label": "name",
        "beforeExpr": false,
        "startsExpr": true,
        "rightAssociative": false,
        "isLoop": false,
        "isAssign": false,
        "prefix": false,
        "postfix": false,
        "binop": null
      },
      "value": "lastname",
      "start": 424,
      "end": 432,
      "loc": {
        "start": {
          "line": 10,
          "column": 52
        },
        "end": {
          "line": 10,
          "column": 60
        }
      }
    },
    {
      "type": {
        "label": ",",
        "beforeExpr": true,
        "startsExpr": false,
        "rightAssociative": false,
        "isLoop": false,
        "isAssign": false,
        "prefix": false,
        "postfix": false,
        "binop": null,
        "updateContext": null
      },
      "start": 432,
      "end": 433,
      "loc": {
        "start": {
          "line": 10,
          "column": 60
        },
        "end": {
          "line": 10,
          "column": 61
        }
      }
    },
    {
      "type": {
        "label": "name",
        "beforeExpr": false,
        "startsExpr": true,
        "rightAssociative": false,
        "isLoop": false,
        "isAssign": false,
        "prefix": false,
        "postfix": false,
        "binop": null
      },
      "value": "email",
      "start": 434,
      "end": 439,
      "loc": {
        "start": {
          "line": 10,
          "column": 62
        },
        "end": {
          "line": 10,
          "column": 67
        }
      }
    },
    {
      "type": {
        "label": ",",
        "beforeExpr": true,
        "startsExpr": false,
        "rightAssociative": false,
        "isLoop": false,
        "isAssign": false,
        "prefix": false,
        "postfix": false,
        "binop": null,
        "updateContext": null
      },
      "start": 439,
      "end": 440,
      "loc": {
        "start": {
          "line": 10,
          "column": 67
        },
        "end": {
          "line": 10,
          "column": 68
        }
      }
    },
    {
      "type": {
        "label": "name",
        "beforeExpr": false,
        "startsExpr": true,
        "rightAssociative": false,
        "isLoop": false,
        "isAssign": false,
        "prefix": false,
        "postfix": false,
        "binop": null
      },
      "value": "password",
      "start": 441,
      "end": 449,
      "loc": {
        "start": {
          "line": 10,
          "column": 69
        },
        "end": {
          "line": 10,
          "column": 77
        }
      }
    },
    {
      "type": {
        "label": ")",
        "beforeExpr": false,
        "startsExpr": false,
        "rightAssociative": false,
        "isLoop": false,
        "isAssign": false,
        "prefix": false,
        "postfix": false,
        "binop": null
      },
      "start": 449,
      "end": 450,
      "loc": {
        "start": {
          "line": 10,
          "column": 77
        },
        "end": {
          "line": 10,
          "column": 78
        }
      }
    },
    {
      "type": {
        "label": "=>",
        "beforeExpr": true,
        "startsExpr": false,
        "rightAssociative": false,
        "isLoop": false,
        "isAssign": false,
        "prefix": false,
        "postfix": false,
        "binop": null,
        "updateContext": null
      },
      "start": 451,
      "end": 453,
      "loc": {
        "start": {
          "line": 10,
          "column": 79
        },
        "end": {
          "line": 10,
          "column": 81
        }
      }
    },
    {
      "type": {
        "label": "(",
        "beforeExpr": true,
        "startsExpr": true,
        "rightAssociative": false,
        "isLoop": false,
        "isAssign": false,
        "prefix": false,
        "postfix": false,
        "binop": null
      },
      "start": 454,
      "end": 455,
      "loc": {
        "start": {
          "line": 10,
          "column": 82
        },
        "end": {
          "line": 10,
          "column": 83
        }
      }
    },
    {
      "type": {
        "label": "{",
        "beforeExpr": true,
        "startsExpr": true,
        "rightAssociative": false,
        "isLoop": false,
        "isAssign": false,
        "prefix": false,
        "postfix": false,
        "binop": null
      },
      "start": 455,
      "end": 456,
      "loc": {
        "start": {
          "line": 10,
          "column": 83
        },
        "end": {
          "line": 10,
          "column": 84
        }
      }
    },
    {
      "type": {
        "label": "name",
        "beforeExpr": false,
        "startsExpr": true,
        "rightAssociative": false,
        "isLoop": false,
        "isAssign": false,
        "prefix": false,
        "postfix": false,
        "binop": null
      },
      "value": "type",
      "start": 461,
      "end": 465,
      "loc": {
        "start": {
          "line": 11,
          "column": 4
        },
        "end": {
          "line": 11,
          "column": 8
        }
      }
    },
    {
      "type": {
        "label": ":",
        "beforeExpr": true,
        "startsExpr": false,
        "rightAssociative": false,
        "isLoop": false,
        "isAssign": false,
        "prefix": false,
        "postfix": false,
        "binop": null,
        "updateContext": null
      },
      "start": 465,
      "end": 466,
      "loc": {
        "start": {
          "line": 11,
          "column": 8
        },
        "end": {
          "line": 11,
          "column": 9
        }
      }
    },
    {
      "type": {
        "label": "string",
        "beforeExpr": false,
        "startsExpr": true,
        "rightAssociative": false,
        "isLoop": false,
        "isAssign": false,
        "prefix": false,
        "postfix": false,
        "binop": null,
        "updateContext": null
      },
      "value": "SUBMIT_REGISTER",
      "start": 467,
      "end": 484,
      "loc": {
        "start": {
          "line": 11,
          "column": 10
        },
        "end": {
          "line": 11,
          "column": 27
        }
      }
    },
    {
      "type": {
        "label": ",",
        "beforeExpr": true,
        "startsExpr": false,
        "rightAssociative": false,
        "isLoop": false,
        "isAssign": false,
        "prefix": false,
        "postfix": false,
        "binop": null,
        "updateContext": null
      },
      "start": 484,
      "end": 485,
      "loc": {
        "start": {
          "line": 11,
          "column": 27
        },
        "end": {
          "line": 11,
          "column": 28
        }
      }
    },
    {
      "type": {
        "label": "name",
        "beforeExpr": false,
        "startsExpr": true,
        "rightAssociative": false,
        "isLoop": false,
        "isAssign": false,
        "prefix": false,
        "postfix": false,
        "binop": null
      },
      "value": "username",
      "start": 490,
      "end": 498,
      "loc": {
        "start": {
          "line": 12,
          "column": 4
        },
        "end": {
          "line": 12,
          "column": 12
        }
      }
    },
    {
      "type": {
        "label": ",",
        "beforeExpr": true,
        "startsExpr": false,
        "rightAssociative": false,
        "isLoop": false,
        "isAssign": false,
        "prefix": false,
        "postfix": false,
        "binop": null,
        "updateContext": null
      },
      "start": 498,
      "end": 499,
      "loc": {
        "start": {
          "line": 12,
          "column": 12
        },
        "end": {
          "line": 12,
          "column": 13
        }
      }
    },
    {
      "type": {
        "label": "name",
        "beforeExpr": false,
        "startsExpr": true,
        "rightAssociative": false,
        "isLoop": false,
        "isAssign": false,
        "prefix": false,
        "postfix": false,
        "binop": null
      },
      "value": "firstname",
      "start": 504,
      "end": 513,
      "loc": {
        "start": {
          "line": 13,
          "column": 4
        },
        "end": {
          "line": 13,
          "column": 13
        }
      }
    },
    {
      "type": {
        "label": ",",
        "beforeExpr": true,
        "startsExpr": false,
        "rightAssociative": false,
        "isLoop": false,
        "isAssign": false,
        "prefix": false,
        "postfix": false,
        "binop": null,
        "updateContext": null
      },
      "start": 513,
      "end": 514,
      "loc": {
        "start": {
          "line": 13,
          "column": 13
        },
        "end": {
          "line": 13,
          "column": 14
        }
      }
    },
    {
      "type": {
        "label": "name",
        "beforeExpr": false,
        "startsExpr": true,
        "rightAssociative": false,
        "isLoop": false,
        "isAssign": false,
        "prefix": false,
        "postfix": false,
        "binop": null
      },
      "value": "lastname",
      "start": 519,
      "end": 527,
      "loc": {
        "start": {
          "line": 14,
          "column": 4
        },
        "end": {
          "line": 14,
          "column": 12
        }
      }
    },
    {
      "type": {
        "label": ",",
        "beforeExpr": true,
        "startsExpr": false,
        "rightAssociative": false,
        "isLoop": false,
        "isAssign": false,
        "prefix": false,
        "postfix": false,
        "binop": null,
        "updateContext": null
      },
      "start": 527,
      "end": 528,
      "loc": {
        "start": {
          "line": 14,
          "column": 12
        },
        "end": {
          "line": 14,
          "column": 13
        }
      }
    },
    {
      "type": {
        "label": "name",
        "beforeExpr": false,
        "startsExpr": true,
        "rightAssociative": false,
        "isLoop": false,
        "isAssign": false,
        "prefix": false,
        "postfix": false,
        "binop": null
      },
      "value": "email",
      "start": 533,
      "end": 538,
      "loc": {
        "start": {
          "line": 15,
          "column": 4
        },
        "end": {
          "line": 15,
          "column": 9
        }
      }
    },
    {
      "type": {
        "label": ",",
        "beforeExpr": true,
        "startsExpr": false,
        "rightAssociative": false,
        "isLoop": false,
        "isAssign": false,
        "prefix": false,
        "postfix": false,
        "binop": null,
        "updateContext": null
      },
      "start": 538,
      "end": 539,
      "loc": {
        "start": {
          "line": 15,
          "column": 9
        },
        "end": {
          "line": 15,
          "column": 10
        }
      }
    },
    {
      "type": {
        "label": "name",
        "beforeExpr": false,
        "startsExpr": true,
        "rightAssociative": false,
        "isLoop": false,
        "isAssign": false,
        "prefix": false,
        "postfix": false,
        "binop": null
      },
      "value": "password",
      "start": 544,
      "end": 552,
      "loc": {
        "start": {
          "line": 16,
          "column": 4
        },
        "end": {
          "line": 16,
          "column": 12
        }
      }
    },
    {
      "type": {
        "label": "}",
        "beforeExpr": false,
        "startsExpr": false,
        "rightAssociative": false,
        "isLoop": false,
        "isAssign": false,
        "prefix": false,
        "postfix": false,
        "binop": null
      },
      "start": 553,
      "end": 554,
      "loc": {
        "start": {
          "line": 17,
          "column": 0
        },
        "end": {
          "line": 17,
          "column": 1
        }
      }
    },
    {
      "type": {
        "label": ")",
        "beforeExpr": false,
        "startsExpr": false,
        "rightAssociative": false,
        "isLoop": false,
        "isAssign": false,
        "prefix": false,
        "postfix": false,
        "binop": null
      },
      "start": 554,
      "end": 555,
      "loc": {
        "start": {
          "line": 17,
          "column": 1
        },
        "end": {
          "line": 17,
          "column": 2
        }
      }
    },
    {
      "type": "CommentBlock",
      "value": "*\n * @return {action} REGISTER_SUCCESS action\n ",
      "start": 557,
      "end": 608,
      "loc": {
        "start": {
          "line": 19,
          "column": 0
        },
        "end": {
          "line": 21,
          "column": 3
        }
      }
    },
    {
      "type": {
        "label": "export",
        "keyword": "export",
        "beforeExpr": false,
        "startsExpr": false,
        "rightAssociative": false,
        "isLoop": false,
        "isAssign": false,
        "prefix": false,
        "postfix": false,
        "binop": null,
        "updateContext": null
      },
      "value": "export",
      "start": 609,
      "end": 615,
      "loc": {
        "start": {
          "line": 22,
          "column": 0
        },
        "end": {
          "line": 22,
          "column": 6
        }
      }
    },
    {
      "type": {
        "label": "const",
        "keyword": "const",
        "beforeExpr": false,
        "startsExpr": false,
        "rightAssociative": false,
        "isLoop": false,
        "isAssign": false,
        "prefix": false,
        "postfix": false,
        "binop": null,
        "updateContext": null
      },
      "value": "const",
      "start": 616,
      "end": 621,
      "loc": {
        "start": {
          "line": 22,
          "column": 7
        },
        "end": {
          "line": 22,
          "column": 12
        }
      }
    },
    {
      "type": {
        "label": "name",
        "beforeExpr": false,
        "startsExpr": true,
        "rightAssociative": false,
        "isLoop": false,
        "isAssign": false,
        "prefix": false,
        "postfix": false,
        "binop": null
      },
      "value": "registerSuccess",
      "start": 622,
      "end": 637,
      "loc": {
        "start": {
          "line": 22,
          "column": 13
        },
        "end": {
          "line": 22,
          "column": 28
        }
      }
    },
    {
      "type": {
        "label": "=",
        "beforeExpr": true,
        "startsExpr": false,
        "rightAssociative": false,
        "isLoop": false,
        "isAssign": true,
        "prefix": false,
        "postfix": false,
        "binop": null,
        "updateContext": null
      },
      "value": "=",
      "start": 638,
      "end": 639,
      "loc": {
        "start": {
          "line": 22,
          "column": 29
        },
        "end": {
          "line": 22,
          "column": 30
        }
      }
    },
    {
      "type": {
        "label": "(",
        "beforeExpr": true,
        "startsExpr": true,
        "rightAssociative": false,
        "isLoop": false,
        "isAssign": false,
        "prefix": false,
        "postfix": false,
        "binop": null
      },
      "start": 640,
      "end": 641,
      "loc": {
        "start": {
          "line": 22,
          "column": 31
        },
        "end": {
          "line": 22,
          "column": 32
        }
      }
    },
    {
      "type": {
        "label": ")",
        "beforeExpr": false,
        "startsExpr": false,
        "rightAssociative": false,
        "isLoop": false,
        "isAssign": false,
        "prefix": false,
        "postfix": false,
        "binop": null
      },
      "start": 641,
      "end": 642,
      "loc": {
        "start": {
          "line": 22,
          "column": 32
        },
        "end": {
          "line": 22,
          "column": 33
        }
      }
    },
    {
      "type": {
        "label": "=>",
        "beforeExpr": true,
        "startsExpr": false,
        "rightAssociative": false,
        "isLoop": false,
        "isAssign": false,
        "prefix": false,
        "postfix": false,
        "binop": null,
        "updateContext": null
      },
      "start": 643,
      "end": 645,
      "loc": {
        "start": {
          "line": 22,
          "column": 34
        },
        "end": {
          "line": 22,
          "column": 36
        }
      }
    },
    {
      "type": {
        "label": "(",
        "beforeExpr": true,
        "startsExpr": true,
        "rightAssociative": false,
        "isLoop": false,
        "isAssign": false,
        "prefix": false,
        "postfix": false,
        "binop": null
      },
      "start": 646,
      "end": 647,
      "loc": {
        "start": {
          "line": 22,
          "column": 37
        },
        "end": {
          "line": 22,
          "column": 38
        }
      }
    },
    {
      "type": {
        "label": "{",
        "beforeExpr": true,
        "startsExpr": true,
        "rightAssociative": false,
        "isLoop": false,
        "isAssign": false,
        "prefix": false,
        "postfix": false,
        "binop": null
      },
      "start": 647,
      "end": 648,
      "loc": {
        "start": {
          "line": 22,
          "column": 38
        },
        "end": {
          "line": 22,
          "column": 39
        }
      }
    },
    {
      "type": {
        "label": "name",
        "beforeExpr": false,
        "startsExpr": true,
        "rightAssociative": false,
        "isLoop": false,
        "isAssign": false,
        "prefix": false,
        "postfix": false,
        "binop": null
      },
      "value": "type",
      "start": 653,
      "end": 657,
      "loc": {
        "start": {
          "line": 23,
          "column": 4
        },
        "end": {
          "line": 23,
          "column": 8
        }
      }
    },
    {
      "type": {
        "label": ":",
        "beforeExpr": true,
        "startsExpr": false,
        "rightAssociative": false,
        "isLoop": false,
        "isAssign": false,
        "prefix": false,
        "postfix": false,
        "binop": null,
        "updateContext": null
      },
      "start": 657,
      "end": 658,
      "loc": {
        "start": {
          "line": 23,
          "column": 8
        },
        "end": {
          "line": 23,
          "column": 9
        }
      }
    },
    {
      "type": {
        "label": "string",
        "beforeExpr": false,
        "startsExpr": true,
        "rightAssociative": false,
        "isLoop": false,
        "isAssign": false,
        "prefix": false,
        "postfix": false,
        "binop": null,
        "updateContext": null
      },
      "value": "REGISTER_SUCCESS",
      "start": 659,
      "end": 677,
      "loc": {
        "start": {
          "line": 23,
          "column": 10
        },
        "end": {
          "line": 23,
          "column": 28
        }
      }
    },
    {
      "type": {
        "label": "}",
        "beforeExpr": false,
        "startsExpr": false,
        "rightAssociative": false,
        "isLoop": false,
        "isAssign": false,
        "prefix": false,
        "postfix": false,
        "binop": null
      },
      "start": 678,
      "end": 679,
      "loc": {
        "start": {
          "line": 24,
          "column": 0
        },
        "end": {
          "line": 24,
          "column": 1
        }
      }
    },
    {
      "type": {
        "label": ")",
        "beforeExpr": false,
        "startsExpr": false,
        "rightAssociative": false,
        "isLoop": false,
        "isAssign": false,
        "prefix": false,
        "postfix": false,
        "binop": null
      },
      "start": 679,
      "end": 680,
      "loc": {
        "start": {
          "line": 24,
          "column": 1
        },
        "end": {
          "line": 24,
          "column": 2
        }
      }
    },
    {
      "type": "CommentBlock",
      "value": "*\n * @param {*} error the error \n * @return {action} REGISTER_ERROR action and the payload with the error\n ",
      "start": 682,
      "end": 793,
      "loc": {
        "start": {
          "line": 26,
          "column": 0
        },
        "end": {
          "line": 29,
          "column": 3
        }
      }
    },
    {
      "type": {
        "label": "export",
        "keyword": "export",
        "beforeExpr": false,
        "startsExpr": false,
        "rightAssociative": false,
        "isLoop": false,
        "isAssign": false,
        "prefix": false,
        "postfix": false,
        "binop": null,
        "updateContext": null
      },
      "value": "export",
      "start": 794,
      "end": 800,
      "loc": {
        "start": {
          "line": 30,
          "column": 0
        },
        "end": {
          "line": 30,
          "column": 6
        }
      }
    },
    {
      "type": {
        "label": "const",
        "keyword": "const",
        "beforeExpr": false,
        "startsExpr": false,
        "rightAssociative": false,
        "isLoop": false,
        "isAssign": false,
        "prefix": false,
        "postfix": false,
        "binop": null,
        "updateContext": null
      },
      "value": "const",
      "start": 801,
      "end": 806,
      "loc": {
        "start": {
          "line": 30,
          "column": 7
        },
        "end": {
          "line": 30,
          "column": 12
        }
      }
    },
    {
      "type": {
        "label": "name",
        "beforeExpr": false,
        "startsExpr": true,
        "rightAssociative": false,
        "isLoop": false,
        "isAssign": false,
        "prefix": false,
        "postfix": false,
        "binop": null
      },
      "value": "registerError",
      "start": 807,
      "end": 820,
      "loc": {
        "start": {
          "line": 30,
          "column": 13
        },
        "end": {
          "line": 30,
          "column": 26
        }
      }
    },
    {
      "type": {
        "label": "=",
        "beforeExpr": true,
        "startsExpr": false,
        "rightAssociative": false,
        "isLoop": false,
        "isAssign": true,
        "prefix": false,
        "postfix": false,
        "binop": null,
        "updateContext": null
      },
      "value": "=",
      "start": 821,
      "end": 822,
      "loc": {
        "start": {
          "line": 30,
          "column": 27
        },
        "end": {
          "line": 30,
          "column": 28
        }
      }
    },
    {
      "type": {
        "label": "(",
        "beforeExpr": true,
        "startsExpr": true,
        "rightAssociative": false,
        "isLoop": false,
        "isAssign": false,
        "prefix": false,
        "postfix": false,
        "binop": null
      },
      "start": 823,
      "end": 824,
      "loc": {
        "start": {
          "line": 30,
          "column": 29
        },
        "end": {
          "line": 30,
          "column": 30
        }
      }
    },
    {
      "type": {
        "label": "name",
        "beforeExpr": false,
        "startsExpr": true,
        "rightAssociative": false,
        "isLoop": false,
        "isAssign": false,
        "prefix": false,
        "postfix": false,
        "binop": null
      },
      "value": "error",
      "start": 824,
      "end": 829,
      "loc": {
        "start": {
          "line": 30,
          "column": 30
        },
        "end": {
          "line": 30,
          "column": 35
        }
      }
    },
    {
      "type": {
        "label": ")",
        "beforeExpr": false,
        "startsExpr": false,
        "rightAssociative": false,
        "isLoop": false,
        "isAssign": false,
        "prefix": false,
        "postfix": false,
        "binop": null
      },
      "start": 829,
      "end": 830,
      "loc": {
        "start": {
          "line": 30,
          "column": 35
        },
        "end": {
          "line": 30,
          "column": 36
        }
      }
    },
    {
      "type": {
        "label": "=>",
        "beforeExpr": true,
        "startsExpr": false,
        "rightAssociative": false,
        "isLoop": false,
        "isAssign": false,
        "prefix": false,
        "postfix": false,
        "binop": null,
        "updateContext": null
      },
      "start": 831,
      "end": 833,
      "loc": {
        "start": {
          "line": 30,
          "column": 37
        },
        "end": {
          "line": 30,
          "column": 39
        }
      }
    },
    {
      "type": {
        "label": "(",
        "beforeExpr": true,
        "startsExpr": true,
        "rightAssociative": false,
        "isLoop": false,
        "isAssign": false,
        "prefix": false,
        "postfix": false,
        "binop": null
      },
      "start": 834,
      "end": 835,
      "loc": {
        "start": {
          "line": 30,
          "column": 40
        },
        "end": {
          "line": 30,
          "column": 41
        }
      }
    },
    {
      "type": {
        "label": "{",
        "beforeExpr": true,
        "startsExpr": true,
        "rightAssociative": false,
        "isLoop": false,
        "isAssign": false,
        "prefix": false,
        "postfix": false,
        "binop": null
      },
      "start": 835,
      "end": 836,
      "loc": {
        "start": {
          "line": 30,
          "column": 41
        },
        "end": {
          "line": 30,
          "column": 42
        }
      }
    },
    {
      "type": {
        "label": "name",
        "beforeExpr": false,
        "startsExpr": true,
        "rightAssociative": false,
        "isLoop": false,
        "isAssign": false,
        "prefix": false,
        "postfix": false,
        "binop": null
      },
      "value": "type",
      "start": 841,
      "end": 845,
      "loc": {
        "start": {
          "line": 31,
          "column": 4
        },
        "end": {
          "line": 31,
          "column": 8
        }
      }
    },
    {
      "type": {
        "label": ":",
        "beforeExpr": true,
        "startsExpr": false,
        "rightAssociative": false,
        "isLoop": false,
        "isAssign": false,
        "prefix": false,
        "postfix": false,
        "binop": null,
        "updateContext": null
      },
      "start": 845,
      "end": 846,
      "loc": {
        "start": {
          "line": 31,
          "column": 8
        },
        "end": {
          "line": 31,
          "column": 9
        }
      }
    },
    {
      "type": {
        "label": "string",
        "beforeExpr": false,
        "startsExpr": true,
        "rightAssociative": false,
        "isLoop": false,
        "isAssign": false,
        "prefix": false,
        "postfix": false,
        "binop": null,
        "updateContext": null
      },
      "value": "REGISTER_ERROR",
      "start": 847,
      "end": 863,
      "loc": {
        "start": {
          "line": 31,
          "column": 10
        },
        "end": {
          "line": 31,
          "column": 26
        }
      }
    },
    {
      "type": {
        "label": ",",
        "beforeExpr": true,
        "startsExpr": false,
        "rightAssociative": false,
        "isLoop": false,
        "isAssign": false,
        "prefix": false,
        "postfix": false,
        "binop": null,
        "updateContext": null
      },
      "start": 863,
      "end": 864,
      "loc": {
        "start": {
          "line": 31,
          "column": 26
        },
        "end": {
          "line": 31,
          "column": 27
        }
      }
    },
    {
      "type": {
        "label": "name",
        "beforeExpr": false,
        "startsExpr": true,
        "rightAssociative": false,
        "isLoop": false,
        "isAssign": false,
        "prefix": false,
        "postfix": false,
        "binop": null
      },
      "value": "payload",
      "start": 869,
      "end": 876,
      "loc": {
        "start": {
          "line": 32,
          "column": 4
        },
        "end": {
          "line": 32,
          "column": 11
        }
      }
    },
    {
      "type": {
        "label": ":",
        "beforeExpr": true,
        "startsExpr": false,
        "rightAssociative": false,
        "isLoop": false,
        "isAssign": false,
        "prefix": false,
        "postfix": false,
        "binop": null,
        "updateContext": null
      },
      "start": 876,
      "end": 877,
      "loc": {
        "start": {
          "line": 32,
          "column": 11
        },
        "end": {
          "line": 32,
          "column": 12
        }
      }
    },
    {
      "type": {
        "label": "name",
        "beforeExpr": false,
        "startsExpr": true,
        "rightAssociative": false,
        "isLoop": false,
        "isAssign": false,
        "prefix": false,
        "postfix": false,
        "binop": null
      },
      "value": "error",
      "start": 878,
      "end": 883,
      "loc": {
        "start": {
          "line": 32,
          "column": 13
        },
        "end": {
          "line": 32,
          "column": 18
        }
      }
    },
    {
      "type": {
        "label": "}",
        "beforeExpr": false,
        "startsExpr": false,
        "rightAssociative": false,
        "isLoop": false,
        "isAssign": false,
        "prefix": false,
        "postfix": false,
        "binop": null
      },
      "start": 884,
      "end": 885,
      "loc": {
        "start": {
          "line": 33,
          "column": 0
        },
        "end": {
          "line": 33,
          "column": 1
        }
      }
    },
    {
      "type": {
        "label": ")",
        "beforeExpr": false,
        "startsExpr": false,
        "rightAssociative": false,
        "isLoop": false,
        "isAssign": false,
        "prefix": false,
        "postfix": false,
        "binop": null
      },
      "start": 885,
      "end": 886,
      "loc": {
        "start": {
          "line": 33,
          "column": 1
        },
        "end": {
          "line": 33,
          "column": 2
        }
      }
    },
    {
      "type": {
        "label": "eof",
        "beforeExpr": false,
        "startsExpr": false,
        "rightAssociative": false,
        "isLoop": false,
        "isAssign": false,
        "prefix": false,
        "postfix": false,
        "binop": null,
        "updateContext": null
      },
      "start": 886,
      "end": 886,
      "loc": {
        "start": {
          "line": 33,
          "column": 2
        },
        "end": {
          "line": 33,
          "column": 2
        }
      }
    }
  ]
}